pyardourclient/__init__.py
pyardourclient/asyncio.py
pyardourclient/callback.py
pyardourclient/message.py
pyardourclient/websocket.py
pyardourclient-0.1.2.dist-info/LICENSE
pyardourclient-0.1.2.dist-info/METADATA
pyardourclient-0.1.2.dist-info/WHEEL
pyardourclient-0.1.2.dist-info/top_level.txt
pyardourclient-0.1.2.dist-info/RECORD
